autoimport/__init__.py
autoimport/main.py
ultralytics_autoimport-0.0.4.dist-info/licenses/LICENSE
ultralytics_autoimport-0.0.4.dist-info/METADATA
ultralytics_autoimport-0.0.4.dist-info/WHEEL
ultralytics_autoimport-0.0.4.dist-info/top_level.txt
ultralytics_autoimport-0.0.4.dist-info/RECORD
