Metadata-Version: 2.4
Name: ultralytics-autoimport
Version: 0.0.4
Summary: Ultralytics autoimport Python Package
Author-email: Glenn Jocher <glenn.jocher@ultralytics.com>, Mohammed Yasin <yasin@ultralytics.com>
Maintainer-email: Ultralytics <hello@ultralytics.com>
License:                     GNU AFFERO GENERAL PUBLIC LICENSE
Project-URL: Homepage, https://ultralytics.com
Project-URL: Source, https://github.com/ultralytics/autoimport
Project-URL: Documentation, https://docs.ultralytics.com
Project-URL: Bug Reports, https://github.com/ultralytics/autoimport/issues
Project-URL: Changelog, https://github.com/ultralytics/autoimport/releases
Keywords: Ultralytics,autoimport,lazy imports
Classifier: Development Status :: 4 - Beta
Classifier: Intended Audience :: Developers
Classifier: Intended Audience :: Education
Classifier: Intended Audience :: Science/Research
Classifier: License :: OSI Approved :: GNU Affero General Public License v3 or later (AGPLv3+)
Classifier: Programming Language :: Python :: 3
Classifier: Programming Language :: Python :: 3.8
Classifier: Programming Language :: Python :: 3.9
Classifier: Programming Language :: Python :: 3.10
Classifier: Programming Language :: Python :: 3.11
Classifier: Programming Language :: Python :: 3.12
Classifier: Programming Language :: Python :: 3.13
Classifier: Topic :: Software Development
Classifier: Topic :: Scientific/Engineering
Classifier: Topic :: Scientific/Engineering :: Artificial Intelligence
Classifier: Operating System :: POSIX :: Linux
Classifier: Operating System :: MacOS
Classifier: Operating System :: Microsoft :: Windows
Requires-Python: >=3.8
License-File: LICENSE
Provides-Extra: dev
Requires-Dist: numpy; extra == "dev"
Dynamic: license-file
